crypto_extranet.py
crypto_extranet-0.1.dist-info/METADATA
crypto_extranet-0.1.dist-info/WHEEL
crypto_extranet-0.1.dist-info/entry_points.txt
crypto_extranet-0.1.dist-info/top_level.txt
crypto_extranet-0.1.dist-info/RECORD
