Metadata-Version: 2.4
Name: crypto-extranet
Version: 0.1
Summary: Basic client for *.crypto-extranet.com extranets.
Author-email: Julien Palard <julien@palard.fr>
License-Expression: MIT
Project-URL: repository, https://git.afpy.org/mdk/crypto-extranet
Requires-Python: >=3.9
Requires-Dist: requests
Provides-Extra: dev
Requires-Dist: pytest; extra == "dev"
Requires-Dist: tox; extra == "dev"
Requires-Dist: pylint; extra == "dev"
Requires-Dist: mypy; extra == "dev"
Requires-Dist: types-requests; extra == "dev"
Requires-Dist: isort; extra == "dev"
Requires-Dist: black; extra == "dev"
Requires-Dist: ruff; extra == "dev"
